hypermorph/LICENSE.txt
hypermorph/README.md
hypermorph/__init__.py
hypermorph/clients.py
hypermorph/connector_clickhouse_driver.py
hypermorph/connector_mysql.py
hypermorph/connector_sqlalchemy.py
hypermorph/data_graph.py
hypermorph/data_graph_hyperatom.py
hypermorph/data_graph_hyperbond.py
hypermorph/data_graph_link.py
hypermorph/data_graph_node.py
hypermorph/data_pipe.py
hypermorph/draw_hypergraph.py
hypermorph/exceptions.py
hypermorph/hacol.py
hypermorph/hacol_pipe.py
hypermorph/haset.py
hypermorph/haset_pipe.py
hypermorph/hassoc.py
hypermorph/mis.py
hypermorph/requirements_conda.txt
hypermorph/requirements_pip.txt
hypermorph/schema.py
hypermorph/schema_dms_attribute.py
hypermorph/schema_dms_datamodel.py
hypermorph/schema_dms_entity.py
hypermorph/schema_drs_dataset.py
hypermorph/schema_drs_field.py
hypermorph/schema_drs_graph_datamodel.py
hypermorph/schema_drs_graph_schema.py
hypermorph/schema_drs_table.py
hypermorph/schema_link.py
hypermorph/schema_node.py
hypermorph/schema_pipe.py
hypermorph/schema_sys.py
hypermorph/test.py
hypermorph/utils.py
hypermorph/data/DemoData/ASETS/readme.txt
hypermorph/data/DemoData/DataGraphs/readme.txt
hypermorph/data/DemoData/DataModels/spc_model.graphml
hypermorph/data/DemoData/Feather/Physicians/Physician_Compare_fields_aliases.txt
hypermorph/data/DemoData/Feather/Physicians/Physician_Compare_fields_descriptions.txt
hypermorph/data/DemoData/Feather/Physicians/Physician_Compare_profiling.txt
hypermorph/data/DemoData/FlatFiles/SupplierPartCatalog/spc_catalog.tsv
hypermorph/data/DemoData/FlatFiles/SupplierPartCatalog/spc_parts.tsv
hypermorph/data/DemoData/FlatFiles/SupplierPartCatalog/spc_suppliers.tsv
hypermorph/data/DemoData/SQLite/northwind.sqlite
hypermorph/data/DemoData/SQLite/spc.sqlite
hypermorph/data/DemoData/Schemata/readme.txt
hypermorph/data/MySQLDumps/dump-Northwind8Entities-201909061113.sql
hypermorph/data/MySQLDumps/dump-SPC-201909050814.sql
hypermorph/demo/add_aset_from_additional_data_resource.py
hypermorph-0.1.2.dist-info/LICENSE.txt
hypermorph-0.1.2.dist-info/METADATA
hypermorph-0.1.2.dist-info/WHEEL
hypermorph-0.1.2.dist-info/top_level.txt
hypermorph-0.1.2.dist-info/RECORD
